{
  "name":"mycluster",
  "children":
  [
    {
      "name":"hbase",
      "children":
        [
          {
            "name":"hm",
            "children":
            [
              {
                "name":"ha",
                "children":[
                  {
                    "name":"node1",
                    "ip":"192.168.0.1"
                  }
                ]
              },
              {
                "name":"hs",
                "children":[
                  {
                    "name":"node2",
                    "ip":"192.168.0.2"
                  }
                ]
              }
            ]
          },
          {
            "name":"rs",
            "children":
              [
                {
                  "name":"node1",
                  "ip":"192.168.0.1"
                },
                {
                  "name":"node2",
                  "ip":"192.168.0.2"
                },
                {
                  "name":"node3",
                  "ip":"192.168.0.3"
                },
                {
                  "name":"node4",
                  "ip":"192.168.0.4"
                }
              ]
          }
        ]
    },
    {
      "name":"zookeeper",
      "children":
      [
        {
          "name":"node1",
          "ip":"192.168.0.1"
        },
        {
          "name":"node2",
          "ip":"192.168.0.2"
        },
        {
          "name":"node3",
          "ip":"192.168.0.3"
        }
      ]
    }
  ]
}
